mvport/__init__.py
mvport/portfolio.py
mvport/stock.py
mvport/utils.py
mvport-1.3.2.dist-info/AUTHORS.rst
mvport-1.3.2.dist-info/LICENSE
mvport-1.3.2.dist-info/METADATA
mvport-1.3.2.dist-info/WHEEL
mvport-1.3.2.dist-info/top_level.txt
mvport-1.3.2.dist-info/RECORD
