Metadata-Version: 2.1
Name: mvport
Version: 1.3.2
Summary: MV Port is a Python package to perform Mean-Variance Analysis. It provides a Portfolio class with a variety of methods to help on your portfolio optimization tasks.
Home-page: https://github.com/condereis/mean-variance-portfolio
Author: Rafael Lopes Conde dos Reis
Author-email: rafael.lcreis@gmail.com
License: MIT license
Keywords: mvport
Classifier: Development Status :: 2 - Pre-Alpha
Classifier: Intended Audience :: Developers
Classifier: License :: OSI Approved :: MIT License
Classifier: Natural Language :: English
Classifier: Programming Language :: Python :: 2
Classifier: Programming Language :: Python :: 2.7
Classifier: Programming Language :: Python :: 3
Classifier: Programming Language :: Python :: 3.4
Classifier: Programming Language :: Python :: 3.5
Classifier: Programming Language :: Python :: 3.6
License-File: LICENSE
License-File: AUTHORS.rst
Requires-Dist: numpy ==2.0.0
Requires-Dist: scipy ==1.14.0
